LICENSE
MANIFEST.in
README.md
setup.py
_stbt/__init__.py
_stbt/android.py
_stbt/black.py
_stbt/config.py
_stbt/cv2_compat.py
_stbt/diff.py
_stbt/frameobject.py
_stbt/grid.py
_stbt/imgproc_cache.py
_stbt/imgutils.py
_stbt/keyboard.py
_stbt/libstbt.py
_stbt/logging.py
_stbt/mask.py
_stbt/match.py
_stbt/motion.py
_stbt/multipress.py
_stbt/ocr.py
_stbt/precondition.py
_stbt/pylint_plugin.py
_stbt/sqdiff.py
_stbt/stbt.conf
_stbt/transition.py
_stbt/types.py
_stbt/utils.py
_stbt/wait.py
stbt_core/__init__.py
stbt_core/pylint_plugin.py
stbt_core.egg-info/PKG-INFO
stbt_core.egg-info/SOURCES.txt
stbt_core.egg-info/dependency_links.txt
stbt_core.egg-info/requires.txt
stbt_core.egg-info/top_level.txt