Metadata-Version: 2.1
Name: stbt-core
Version: 34.10.0
Summary: Automated GUI testing for Set-Top Boxes
Home-page: https://stb-tester.com
Author: Stb-tester.com Ltd.
Author-email: support@stb-tester.com
License: UNKNOWN
Platform: UNKNOWN
Classifier: Development Status :: 5 - Production/Stable
Classifier: License :: OSI Approved :: GNU Lesser General Public License v2 or later (LGPLv2+)
Classifier: Operating System :: OS Independent
Classifier: Programming Language :: Python :: 3.10
Classifier: Topic :: Software Development :: Testing
Requires-Python: >=3.10
Provides-Extra: debug
Provides-Extra: keyboard
Provides-Extra: ocr
License-File: LICENSE
